README.md
setup.cfg
setup.py
ExamLibrary/Numbers1.py
ExamLibrary/Numbers2.py
ExamLibrary/Numbers3.py
ExamLibrary/Numbers4.py
ExamLibrary/__init__.py
ExamLibrary/sdfagereg.py
ExamLibrary.egg-info/PKG-INFO
ExamLibrary.egg-info/SOURCES.txt
ExamLibrary.egg-info/dependency_links.txt
ExamLibrary.egg-info/requires.txt
ExamLibrary.egg-info/top_level.txt