Metadata-Version: 2.1
Name: ExamLibrary
Version: 1.0.0
Summary: Python module for writing scripts for project management platform Club House (clubhouse.io API wrapper)
Home-page: https://github.com/Peopl3s/club-house-api
Download-URL: https://github.com/Peopl3s/club-house-api/archive/main.zip
Author: Peoplees
Author-email: pulratv1@gmail.com
License: Apache License, Version 2.0, see LICENSE file
Classifier: License :: OSI Approved :: Apache Software License
Classifier: Operating System :: OS Independent
Classifier: Intended Audience :: End Users/Desktop
Classifier: Intended Audience :: Developers
Classifier: Programming Language :: Python
Classifier: Programming Language :: Python :: 3
Classifier: Programming Language :: Python :: 3.10
Classifier: Programming Language :: Python :: 3.11
Classifier: Programming Language :: Python :: 3.12
Classifier: Programming Language :: Python :: Implementation :: PyPy
Classifier: Programming Language :: Python :: Implementation :: CPython
Requires-Dist: aiohttp
Requires-Dist: aiofiles
